dongzc1025_mcp_demo/__init__.py
dongzc1025_mcp_demo/weather.py
dongzc1025_mcp_demo-0.1.10.dist-info/METADATA
dongzc1025_mcp_demo-0.1.10.dist-info/WHEEL
dongzc1025_mcp_demo-0.1.10.dist-info/entry_points.txt
dongzc1025_mcp_demo-0.1.10.dist-info/RECORD
