Metadata-Version: 2.4
Name: dongzc1025-mcp-demo
Version: 0.1.10
Summary: Add your description here
Author-email: dongzca <dongzca@digitalchina.com>
Requires-Python: >=3.10
Requires-Dist: mcp[cli]>=1.9.4
